{
  "productos": [
    {
      "nombre": "Jugo de Naranja",
      "precio": "314",
      "id": 3
    },
    {
      "nombre": "Rib Eye 800g",
      "precio": "202",
      "id": 4
    },
    {
      "nombre": "Jugo de Fresa",
      "precio": "201",
      "id": 5
    },
    {
      "nombre": "Calabaza",
      "precio": "101",
      "id": 6
    },
    {
      "nombre": "Calabaza",
      "precio": 200,
      "id": 7
    },
    {
      "nombre": "Calabaza",
      "precio": 66,
      "id": 8
    },
    {
      "nombre": "Calabaza",
      "precio": 1,
      "id": 9
    },
    {
      "nombre": "Calabaza",
      "precio": 1,
      "id": 11
    },
    {
      "nombre": "Calabaza",
      "precio": 2,
      "id": 12
    },
    {
      "nombre": "Calabaza",
      "precio": 3,
      "id": 13
    }
  ]
}